mproxy/__init__.py
mproxy/manager.py
mproxy/proxysession.py
mproxy/proxy/__init__.py
mproxy/proxy/aws.py
mproxy/proxy/awsnord.py
mproxy/proxy/proxy.py
mproxy/proxy/tor.py
mproxy/source/__init__.py
mproxy/source/google.py
mproxy/source/translate.py
mproxy/utils/__init__.py
mproxy/utils/retry.py
mproxy/utils/share.py
mproxy-0.0.7.dist-info/METADATA
mproxy-0.0.7.dist-info/WHEEL
mproxy-0.0.7.dist-info/top_level.txt
mproxy-0.0.7.dist-info/RECORD
