Metadata-Version: 2.1
Name: mproxy
Version: 0.0.7
Summary: Mproxy
Home-page: https://github.com/simonm3/mproxy.git
Author: UNKNOWN
Author-email: UNKNOWN
License: UNKNOWN
Platform: UNKNOWN
Requires-Dist: fabric
Requires-Dist: pandas
Requires-Dist: stem
Requires-Dist: apache-libcloud
Requires-Dist: requests
Requires-Dist: beautifulsoup4
Requires-Dist: googletrans
